Metadata-Version: 1.0
Name: otis
Version: 0.0.1
Summary: Open Timeseries Interface Service
Home-page: https://github.com/hodgesds/otis-python
Author: Daniel Hodges
Author-email: hodges.daniel.scott@gmail.com
License: UNKNOWN
Platform: UNKNOWN
